README.md
setup.py
dirlistproc/DirectoryListProcessor.py
dirlistproc/__init__.py
dirlistproc.egg-info/PKG-INFO
dirlistproc.egg-info/SOURCES.txt
dirlistproc.egg-info/dependency_links.txt
dirlistproc.egg-info/top_level.txt