Metadata-Version: 1.1
Name: dirlistproc
Version: 1.4.5
Summary: Directory list wrapper for batch file processing
Home-page: http://github.com/hsolbrig/dirlistproc
Author: Harold Solbrig
Author-email: solbrig.harold@mayo.edu
License: BSD
Platform: UNKNOWN
Classifier: Development Status :: 4 - Beta
Classifier: Environment :: Console
Classifier: Intended Audience :: Developers
Classifier: License :: OSI Approved :: MIT License
Classifier: Programming Language :: Python
Classifier: Programming Language :: Python :: 3
Classifier: Programming Language :: Python :: 3 :: Only
Classifier: Topic :: Utilities
Classifier: Topic :: Text Processing
